audit_repo_clone_test/__init__.py
audit_repo_clone_test/__version__.py
audit_repo_clone_test/constants.py
audit_repo_clone_test/create_action.py
audit_repo_clone_test/create_audit_repo.py
audit_repo_clone_test/create_secret.py
audit_repo_clone_test-0.2.0.dist-info/LICENSE
audit_repo_clone_test-0.2.0.dist-info/METADATA
audit_repo_clone_test-0.2.0.dist-info/WHEEL
audit_repo_clone_test-0.2.0.dist-info/entry_points.txt
audit_repo_clone_test-0.2.0.dist-info/top_level.txt
audit_repo_clone_test-0.2.0.dist-info/RECORD
