Metadata-Version: 2.1
Name: audit-repo-clone-test
Version: 0.2.0
Home-page: https://github.com/bensacc/audit-repo-cloner.git
Author: DarqBen
License: MIT
Classifier: Development Status :: 2 - Pre-Alpha
Classifier: Intended Audience :: Developers
Classifier: License :: OSI Approved :: MIT License
Classifier: Programming Language :: Python :: 3.7
Classifier: Programming Language :: Python :: 3.8
Classifier: Programming Language :: Python :: 3.9
Classifier: Programming Language :: Python :: 3.10
Requires-Python: >=3.7, <4
License-File: LICENSE
Requires-Dist: certifi
Requires-Dist: cffi
Requires-Dist: charset-normalizer
Requires-Dist: cryptography
Requires-Dist: Deprecated
Requires-Dist: exceptiongroup
Requires-Dist: idna
Requires-Dist: iniconfig
Requires-Dist: packaging
Requires-Dist: pluggy
Requires-Dist: pycparser
Requires-Dist: PyGithub
Requires-Dist: PyJWT
Requires-Dist: PyNaCl
Requires-Dist: pytest
Requires-Dist: python-dotenv
Requires-Dist: requests
Requires-Dist: tomli
Requires-Dist: urllib3
Requires-Dist: wrapt
